pythontexfigures/__init__.py
pythontexfigures/install.py
pythontexfigures/pythontexfigures.py
pythontexfigures/pythontexfigures.sty
pythontexfigures/sty.py
pythontexfigures-0.2.0.dist-info/LICENSE
pythontexfigures-0.2.0.dist-info/METADATA
pythontexfigures-0.2.0.dist-info/WHEEL
pythontexfigures-0.2.0.dist-info/top_level.txt
pythontexfigures-0.2.0.dist-info/RECORD
