Metadata-Version: 2.1
Name: pythontexfigures
Version: 0.2.0
Summary: Embed matplotlib figures into LaTeX documents using PythonTeX
Home-page: https://github.com/mje-nz/pythontexfigures
Author: Matthew Edwards
License: BSD 3-Clause
Platform: UNKNOWN
Classifier: Development Status :: 3 - Alpha
Classifier: Intended Audience :: Science/Research
Classifier: License :: OSI Approved :: BSD License
Classifier: Operating System :: MacOS :: MacOS X
Classifier: Operating System :: POSIX :: Linux
Classifier: Programming Language :: Python :: 3
Classifier: Programming Language :: Python :: 3.5
Classifier: Programming Language :: Python :: 3.6
Classifier: Programming Language :: Python :: 3.7
Classifier: Topic :: Text Processing :: Markup :: LaTeX
Requires-Python: >=3.5
Requires-Dist: matplotlib
Requires-Dist: pygments
